LICENSE
MANIFEST.in
README.md
requirements.txt
setup.py
aws_sam_cli_local.egg-info/PKG-INFO
aws_sam_cli_local.egg-info/SOURCES.txt
aws_sam_cli_local.egg-info/dependency_links.txt
aws_sam_cli_local.egg-info/not-zip-safe
aws_sam_cli_local.egg-info/requires.txt
aws_sam_cli_local.egg-info/top_level.txt
bin/samlocal
bin/samlocal.bat
sample/__init__.py
sample/hello_world/__init__.py
sample/hello_world/app.py