Metadata-Version: 2.1
Name: aws-sam-cli-local
Version: 1.70.0
Summary: Simple wrapper around AWS SAM CLI for use with LocalStack
Home-page: https://github.com/localstack/aws-sam-cli-local
Author: LocalStack Team
Author-email: info@localstack.cloud
License: Apache License 2.0
Classifier: Programming Language :: Python :: 3
Classifier: Programming Language :: Python :: 3.6
Classifier: Programming Language :: Python :: 3.7
Classifier: Programming Language :: Python :: 3.8
Classifier: Programming Language :: Python :: 3.9
Classifier: Programming Language :: Python :: 3.10
Classifier: License :: OSI Approved :: Apache Software License
Classifier: Topic :: Software Development :: Testing
Provides-Extra: dev
License-File: LICENSE
